abstractTradeSimpleT/__init__.py
abstractTradeSimpleT/lib/__init__.py
abstractTradeSimpleT/lib/initialization.py
abstractTradeSimpleT/lib/rates.py
abstractTradeSimpleT/lib/tick.py
abstractTradeSimpleT/lib/timeframe.py
abstractTradeSimpleT/lib/trade.py
src/__init__.py
abstractTradeSimpleT-0.1.22.dist-info/METADATA
abstractTradeSimpleT-0.1.22.dist-info/WHEEL
abstractTradeSimpleT-0.1.22.dist-info/top_level.txt
abstractTradeSimpleT-0.1.22.dist-info/RECORD
