Metadata-Version: 2.1
Name: abstractTradeSimpleT
Version: 0.1.22
Summary: UNKNOWN
Home-page: UNKNOWN
Author: Joao Paulo Euko
License: MIT
Platform: UNKNOWN
Requires-Dist: setuptools (~=59.1.1)
